script/__init__.py
script/ucas-wifi.py
script/ucas_wifi.py
ucas_wifi-1.0.0.dist-info/License
ucas_wifi-1.0.0.dist-info/METADATA
ucas_wifi-1.0.0.dist-info/WHEEL
ucas_wifi-1.0.0.dist-info/entry_points.txt
ucas_wifi-1.0.0.dist-info/top_level.txt
ucas_wifi-1.0.0.dist-info/RECORD
