Metadata-Version: 2.1
Name: ucas-wifi
Version: 1.0.0
Summary: login ucas wifi in terminal
Home-page: https://github.com/iansmith123/ucas-wifi
Author: Les1ie
Author-email: me@les1ie.com
License: GPL v3
Platform: UNKNOWN
Requires-Dist: requests
